psgfiglet/LICENSE.txt
psgfiglet/README.md
psgfiglet/__init__.py
psgfiglet/__main__.py
psgfiglet/psgfiglet.py
psgfiglet/screenshot.jpg
psgfiglet/screenshot.png
psgfiglet-5.0.0.dist-info/LICENSE.txt
psgfiglet-5.0.0.dist-info/METADATA
psgfiglet-5.0.0.dist-info/WHEEL
psgfiglet-5.0.0.dist-info/entry_points.txt
psgfiglet-5.0.0.dist-info/top_level.txt
psgfiglet-5.0.0.dist-info/RECORD
